MANIFEST.in
README.txt
setup.cfg
setup.py
docs/HISTORY.txt
docs/INSTALL.txt
docs/LICENSE.GPL
docs/LICENSE.txt
gloss/__init__.py
gloss.policy.egg-info/PKG-INFO
gloss.policy.egg-info/SOURCES.txt
gloss.policy.egg-info/dependency_links.txt
gloss.policy.egg-info/entry_points.txt
gloss.policy.egg-info/namespace_packages.txt
gloss.policy.egg-info/not-zip-safe
gloss.policy.egg-info/requires.txt
gloss.policy.egg-info/top_level.txt
gloss/policy/__init__.py
gloss/policy/configure.zcml
gloss/policy/tests.py
gloss/policy/profiles/default/metadata.xml
gloss/policy/profiles/default/registry.xml