Metadata-Version: 1.1
Name: gloss.policy
Version: 0.5.1
Summary: Gloss Installer
Home-page: http://svn.plone.org/svn/collective/
Author: UNKNOWN
Author-email: UNKNOWN
License: GPL
Platform: UNKNOWN
Classifier: Framework :: Plone
Classifier: Programming Language :: Python
